post_qa-1.3.3.dist-info/DESCRIPTION.rst
post_qa-1.3.3.dist-info/METADATA
post_qa-1.3.3.dist-info/RECORD
post_qa-1.3.3.dist-info/WHEEL
post_qa-1.3.3.dist-info/entry_points.txt
post_qa-1.3.3.dist-info/metadata.json
post_qa-1.3.3.dist-info/top_level.txt
postqa/__init__.py
postqa/cli.py
postqa/jenkinsenv.py
postqa/jsonshim.py
postqa/lsstsw.py
postqa/pkgdata.py
postqa/schemas.py
postqa/schemas/job.json
postqa/schemas/metric.json
