Metadata-Version: 2.0
Name: post-qa
Version: 1.3.3
Summary: Upload QA metrics for LSST Data Management.
Home-page: https://github.com/lsst-sqre/post-qa
Author: Jonathan Sick
Author-email: jsick@lsst.org
License: MIT
Keywords: lsst
Platform: UNKNOWN
Classifier: Development Status :: 5 - Production/Stable
Classifier: License :: OSI Approved :: MIT License
Classifier: Programming Language :: Python :: 2.7
Classifier: Programming Language :: Python :: 3.4
Classifier: Programming Language :: Python :: 3.5
Requires-Dist: GitPython (>=2.0.3)
Requires-Dist: future (>=0.15.2)
Requires-Dist: jsonschema (>=2.5.1)
Requires-Dist: pytz (>=2016.4)
Requires-Dist: pyyaml (>=3.12)
Requires-Dist: requests (>=2.10.0)
Requires-Dist: rfc3987 (==1.3.7)
Requires-Dist: strict-rfc3339 (==0.7)
